[{"id":1,"mode":"date","type":"date","label":"Date de naissance","key":"date_de_naissance","modalities":[]},{"id":2,"label":"Genre","mode":"mono","type":"list","key":"genre","modalities":[{"label":"Homme","value":"homme"},{"label":"Femme","value":"femme"}]},{"id":3,"label":"Commune","mode":"option","key":"commune","type":"list","modalities":[{"label":"Bandalungwa","value":"bandalungwa"},{"label":"Barumbu","value":"barumbu"},{"label":"Bumbu","value":"bumbu"},{"label":"Gombe","value":"gombe"},{"label":"Kalamu","value":"kalamu"},{"label":"Kasa-Vubu","value":"kasa-vubu"},{"label":"Kimbanseke","value":"kimbanseke"},{"label":"Kinshasa","value":"kinshasa"},{"label":"Kintambo","value":"kintambo"},{"label":"Kisenso","value":"kisenso"},{"label":"Lemba","value":"lemba"},{"label":"Limete","value":"limete"},{"label":"Lingwala","value":"lingwala"},{"label":"Makala","value":"makala"},{"label":"Maluku","value":"maluku"},{"label":"Masina","value":"masina"},{"label":"Matete","value":"matete"},{"label":"Mont-Ngafula","value":"mont-ngafula"},{"label":"Ndjili","value":"ndjili"},{"label":"Ngaba","value":"ngaba"},{"label":"Ngaliema","value":"ngaliema"},{"label":"Ngiringiri","value":"ngiringiri"},{"label":"Nsele","value":"nsele"},{"label":"Selembao","value":"selembao"}]},{"id":4,"label":"Niveau d'éducation","mode":"mono","type":"list","key":"niveau_education","modalities":[{"label":"Pas de diplôme","value":"pas_de_diplome"},{"label":"Diplôme d'études primaires","value":"diplome_d_etudes_primaires"},{"label":"Diplôme d'études secondaires","value":"diplome_d_etudes_secondaires"},{"label":"Diplôme universitaire","value":"diplome_universitaire"},{"label":"Diplôme d'études supérieures","value":"diplome_d_etudes_superieures"}]},{"id":5,"label":"Statut","mode":"mono","type":"list","key":"statut","modalities":[{"label":"Vendeur","value":"vendeur"},{"label":"Acheteur","value":"acheteur"},{"label":"Les deux","value":"vendeur_et_acheteur"}]}]