{"donnee_demographique": {"date_de_naissance": "Sun, 19 Dec 1982 18:03:14 GMT", "genre": "homme", "commune": "barumbu", "niveau_education": "diplome_d_etudes_superieures", "statut": "vendeur_et_acheteur"}, "vendeur": {"numbers": ["0825868229"], "duree_activite": "3_mois", "type_produits_services": ["automobile_accessoires", "instruments_musique", "fournitures_scolaires", "alimentation_boissons", "electroniques_informatiques", "vetements_accessoires"], "reseaux_sociaux_vendre": ["facebook", "whatsapp", "twitter"], "nombre_articles_achetes_vente": "3925", "nombre_articles_vendus": "3338", "nombre_abonnes_pages": [{"facebook": "4477"}, {"whatsapp": "2153"}, {"twitter": "3036"}], "nombre_vues_moyen_publication": [{"facebook": "532"}, {"whatsapp": "841"}, {"twitter": "559"}], "paiement": ["airtel_money", "carte_bancaire", "mpesa_vodacom", "virement_bancaire", "cheque", "orange_money"], "systeme_livraison": "livraison_domicile_transporteur", "defis_commerce_electronique": ["manque_infrastructures_paiement_electroniques_appropriees", "manque_confiance_consommateurs_commerce_electronique"]}, "acheteur": {"numbers": ["0825868229"], "duree_activite": "3_mois", "nombre_achats": "815", "nombre_produits_services": ["alimentation_boissons", "livre_medias", "appareils_electroniques_informatiques", "produits_beaute_soins_personnels", "automobile_accessoires", "vetements_accessoires", "instruments_musique", "fournitures_scolaires"], "r\u00e9seaux_sociaux": ["youtube", "facebook", "telegram", "instagram", "snapchat", "whatsapp", "tiktok", "twitter", "likee"], "paiement": ["carte_bancaire"], "systeme_livraison": "autre", "facteurs_influence": ["qualite_produit", "prix"], "qualite_service_client": 3, "qualite_produits": 2, "recommandation": "non"}}