{"donnee_demographique": {"date_de_naissance": "Thu, 25 Dec 1958 18:03:14 GMT", "genre": "femme", "commune": "makala", "niveau_education": "diplome_d_etudes_primaires", "statut": "acheteur"}, "acheteur": {"numbers": ["0848689738"], "duree_activite": "moins_de_3_mois", "nombre_achats": "529", "nombre_produits_services": ["vetements_accessoires", "alimentation_boissons"], "r\u00e9seaux_sociaux": ["likee"], "paiement": ["airtel_money", "orange_money", "afrimoney", "mpesa", "virement_bancaire"], "systeme_livraison": "livraison_domicile", "facteurs_influence": ["avis_clients", "qualite_produit"], "qualite_service_client": 4, "qualite_produits": 3, "recommandation": "oui"}}