{"donnee_demographique": {"date_de_naissance": "Mon, 15 Dec 1997 18:03:14 GMT", "genre": "homme", "commune": "kintambo", "niveau_education": "diplome_d_etudes_secondaires", "statut": "vendeur"}, "vendeur": {"numbers": ["0850697905"], "duree_activite": "3_mois", "type_produits_services": ["alimentation_boissons", "beaute_soins_personnels", "autres", "fournitures_scolaires", "instruments_musique", "automobile_accessoires", "vetements_accessoires", "electroniques_informatiques"], "reseaux_sociaux_vendre": ["instagram", "twitter", "whatsapp", "facebook", "telegram", "tiktok", "likee", "snapchat"], "nombre_articles_achetes_vente": "968", "nombre_articles_vendus": "390", "nombre_abonnes_pages": [{"instagram": "1713"}, {"twitter": "2442"}, {"whatsapp": "3569"}, {"facebook": "4879"}, {"telegram": "3576"}, {"tiktok": "439"}, {"likee": "461"}, {"snapchat": "3385"}], "nombre_vues_moyen_publication": [{"instagram": "169"}, {"twitter": "2423"}, {"whatsapp": "3431"}, {"facebook": "2903"}, {"telegram": "618"}, {"tiktok": "95"}, {"likee": "119"}, {"snapchat": "1820"}], "paiement": ["cheque", "orange_money", "carte_bancaire", "afrimoney_africell", "mpesa_vodacom"], "systeme_livraison": "pas_de_livraison", "defis_commerce_electronique": ["manque_confiance_consommateurs_commerce_electronique", "manque_infrastructures_paiement_electroniques_appropriees", "problemes_adressage_livraison", "faible_penetration_internet", "difficultes_attirer_fideliser_clients"]}}