{"donnee_demographique": {"date_de_naissance": "Mon, 20 Dec 1976 18:03:14 GMT", "genre": "homme", "commune": "kinshasa", "niveau_education": "diplome_d_etudes_primaires", "statut": "acheteur"}, "acheteur": {"numbers": ["0850419951"], "duree_activite": "3_mois", "nombre_achats": "98", "nombre_produits_services": ["instruments_musique", "vetements_accessoires", "autres", "alimentation_boissons", "produits_beaute_soins_personnels", "fournitures_scolaires", "livre_medias", "appareils_electroniques_informatiques"], "r\u00e9seaux_sociaux": ["snapchat", "tiktok", "facebook", "likee", "telegram", "instagram", "youtube", "twitter", "whatsapp"], "paiement": ["orange_money", "carte_bancaire", "virement_bancaire"], "systeme_livraison": "recuperation_magasin", "facteurs_influence": ["avis_clients"], "qualite_service_client": 6, "qualite_produits": 2, "recommandation": "oui"}}