{"donnee_demographique": {"date_de_naissance": "Sun, 27 Dec 1953 15:46:19 GMT", "genre": "femme", "commune": "mont-ngafula", "niveau_education": "diplome_universitaire", "statut": "vendeur"}, "vendeur": {"numbers": ["0850018863"], "duree_activite": "moins_de_3_mois", "type_produits_services": ["autres", "alimentation_boissons", "instruments_musique"], "reseaux_sociaux_vendre": ["youtube"], "nombre_articles_achetes_vente": "534", "nombre_articles_vendus": "288", "nombre_abonnes_pages": [{"youtube": "3203"}], "nombre_vues_moyen_publication": [{"youtube": "387"}], "paiement": ["airtel_money", "orange_money", "afrimoney_africell", "mpesa_vodacom"], "systeme_livraison": "pas_de_livraison", "defis_commerce_electronique": ["faible_penetration_internet", "difficultes_attirer_fideliser_clients", "manque_confiance_consommateurs_commerce_electronique", "manque_infrastructures_paiement_electroniques_appropriees"]}}