{"donnee_demographique": {"date_de_naissance": "Wed, 21 Dec 1994 03:13:40 GMT", "genre": "homme", "commune": "kasa-vubu", "niveau_education": "diplome_universitaire", "statut": "vendeur"}, "vendeur": {"numbers": ["0859413758"], "duree_activite": "plus_de_3_mois", "type_produits_services": ["fournitures_scolaires", "automobile_accessoires", "alimentation_boissons", "electroniques_informatiques", "vetements_accessoires", "autres"], "reseaux_sociaux_vendre": ["snapchat", "instagram", "whatsapp", "twitter", "likee", "youtube", "tiktok", "telegram"], "nombre_articles_achetes_vente": "104", "nombre_articles_vendus": "88", "nombre_abonnes_pages": [{"snapchat": "3266"}, {"instagram": "1898"}, {"whatsapp": "4107"}, {"twitter": "100"}, {"likee": "4177"}, {"youtube": "3506"}, {"tiktok": "1908"}, {"telegram": "4738"}], "nombre_vues_moyen_publication": [{"snapchat": "2220"}, {"instagram": "617"}, {"whatsapp": "2078"}, {"twitter": "24"}, {"likee": "1527"}, {"youtube": "2570"}, {"tiktok": "1748"}, {"telegram": "4491"}], "paiement": ["carte_bancaire"], "systeme_livraison": "livraison_point_relais", "defis_commerce_electronique": ["manque_infrastructures_paiement_electroniques_appropriees", "faible_penetration_internet", "problemes_adressage_livraison", "difficultes_attirer_fideliser_clients", "manque_confiance_consommateurs_commerce_electronique"]}}